odoo/addons/hr_timesheet_employee_required/README.rst
odoo/addons/hr_timesheet_employee_required/__init__.py
odoo/addons/hr_timesheet_employee_required/__manifest__.py
odoo/addons/hr_timesheet_employee_required/i18n/de.po
odoo/addons/hr_timesheet_employee_required/i18n/es.po
odoo/addons/hr_timesheet_employee_required/i18n/hr_timesheet_employee_required.pot
odoo/addons/hr_timesheet_employee_required/models/__init__.py
odoo/addons/hr_timesheet_employee_required/models/account_analytic_line.py
odoo/addons/hr_timesheet_employee_required/readme/CONTRIBUTORS.rst
odoo/addons/hr_timesheet_employee_required/readme/DESCRIPTION.rst
odoo/addons/hr_timesheet_employee_required/static/description/icon.png
odoo/addons/hr_timesheet_employee_required/static/description/index.html
odoo/addons/hr_timesheet_employee_required/tests/__init__.py
odoo/addons/hr_timesheet_employee_required/tests/test_hr_timesheet_employee_required.py
odoo12_addon_hr_timesheet_employee_required-12.0.1.1.1.dist-info/METADATA
odoo12_addon_hr_timesheet_employee_required-12.0.1.1.1.dist-info/WHEEL
odoo12_addon_hr_timesheet_employee_required-12.0.1.1.1.dist-info/top_level.txt
odoo12_addon_hr_timesheet_employee_required-12.0.1.1.1.dist-info/RECORD
